trackalyzer/__init__.py
trackalyzer/cli.py
trackalyzer-0.1.2.dist-info/entry_points.txt
trackalyzer-0.1.2.dist-info/WHEEL
trackalyzer-0.1.2.dist-info/METADATA
trackalyzer-0.1.2.dist-info/RECORD
